Metadata-Version: 1.1
Name: sqjobs
Version: 0.7.1
Summary: Simple Queue Jobs
Home-page: http://github.com/igalarzab/sqjobs
Author: Jose Ignacio Galarza
Author-email: igalarzab@gmail.com
License: BSD
Platform: any
Classifier: Development Status :: 4 - Beta
Classifier: Intended Audience :: Developers
Classifier: License :: OSI Approved :: BSD License
Classifier: Operating System :: POSIX
Classifier: Operating System :: MacOS
Classifier: Operating System :: Unix
Classifier: Programming Language :: Python
Classifier: Programming Language :: Python :: 2
Classifier: Programming Language :: Python :: 3
Classifier: Topic :: Software Development :: Libraries :: Python Modules
Classifier: Topic :: Internet
Classifier: Topic :: System :: Distributed Computing
Classifier: Topic :: System :: Systems Administration
